{
	"commentStamp" : "cmm 6/6/2008 10:19",
	"super" : "MaObject",
	"category" : "Ma client server-Server API",
	"classinstvars" : [ ],
	"pools" : [ ],
	"classvars" : [
		"ActiveSockets"
	],
	"instvars" : [
		"socketQueue",
		"requestQueue",
		"processRequestProcess",
		"socket",
		"doBlock",
		"port",
		"running",
		"server",
		"socketQueueMonitorProcess",
		"clientConnections",
		"clientConnectionsGuard",
		"preferences",
		"networkProtocol",
		"interface"
	],
	"name" : "MaServerSocket",
	"type" : "normal"
}